Metadata-Version: 2.4
Name: gilda-slim
Version: 1.5.0.1
Summary: Grounding for biomedical entities with contextual disambiguation
Author-email: "Benjamin M. Gyori, Northeastern University" <b.gyori@northeastern.edu>
License: BSD-2-Clause
Project-URL: Homepage, https://github.com/gyorilab/gilda
Project-URL: Documentation, https://gilda.readthedocs.io
Keywords: nlp,biology
Classifier: Development Status :: 4 - Beta
Classifier: Programming Language :: Python :: 3.8
Classifier: Programming Language :: Python :: 3.9
Classifier: Programming Language :: Python :: 3.10
Classifier: Programming Language :: Python :: 3.11
Classifier: Programming Language :: Python :: 3.12
Classifier: Programming Language :: Python :: 3.13
Classifier: Programming Language :: Python :: 3.14
Requires-Python: >=3.8
License-File: LICENSE
Requires-Dist: regex
Requires-Dist: unidecode
Requires-Dist: pystow>=0.1.10
Provides-Extra: test
Requires-Dist: pytest; extra == "test"
Requires-Dist: pytest-cov; extra == "test"
Requires-Dist: pandas; extra == "test"
Provides-Extra: terms
Requires-Dist: indra; extra == "terms"
Requires-Dist: obonet; extra == "terms"
Provides-Extra: benchmarks
Requires-Dist: pandas>=1.0; extra == "benchmarks"
Requires-Dist: requests; extra == "benchmarks"
Requires-Dist: tabulate; extra == "benchmarks"
Requires-Dist: tqdm; extra == "benchmarks"
Requires-Dist: click; extra == "benchmarks"
Provides-Extra: resources
Requires-Dist: boto3; extra == "resources"
Provides-Extra: web
Requires-Dist: flask<4.0,>=3.0; extra == "web"
Requires-Dist: flask-restx>=1.3.0; extra == "web"
Requires-Dist: werkzeug; extra == "web"
Provides-Extra: disambiguation
Requires-Dist: adeft; extra == "disambiguation"
Provides-Extra: ui
Requires-Dist: flask-wtf; extra == "ui"
Requires-Dist: flask-bootstrap; extra == "ui"
Provides-Extra: docs
Requires-Dist: sphinx; extra == "docs"
Requires-Dist: sphinx_autodoc_typehints; extra == "docs"
Requires-Dist: sphinx_rtd_theme; extra == "docs"
Dynamic: license-file
